MJOLNIRGui/__init__.py
MJOLNIRGui/src/__init__.py
MJOLNIRGui/src/build/settings/base.json
MJOLNIRGui/src/build/settings/linux.json
MJOLNIRGui/src/build/settings/mac.json
MJOLNIRGui/src/freeze/windows/MJOLNIR/CalibrationBambus.csv
MJOLNIRGui/src/freeze/windows/MJOLNIR/CalibrationFlatCone.csv
MJOLNIRGui/src/freeze/windows/MJOLNIR/CalibrationMultiFLEXX.csv
MJOLNIRGui/src/freeze/windows/MJOLNIR/Normalization_1.calib
MJOLNIRGui/src/main/icons/Icon.ico
MJOLNIRGui/src/main/icons/MJOLNIRGui.ico
MJOLNIRGui/src/main/icons/README.md
MJOLNIRGui/src/main/icons/base/16.png
MJOLNIRGui/src/main/icons/base/24.png
MJOLNIRGui/src/main/icons/base/32.png
MJOLNIRGui/src/main/icons/base/48.png
MJOLNIRGui/src/main/icons/base/64.png
MJOLNIRGui/src/main/icons/linux/1024.png
MJOLNIRGui/src/main/icons/linux/128.png
MJOLNIRGui/src/main/icons/linux/256.png
MJOLNIRGui/src/main/icons/linux/512.png
MJOLNIRGui/src/main/icons/mac/1024.png
MJOLNIRGui/src/main/icons/mac/128.png
MJOLNIRGui/src/main/icons/mac/256.png
MJOLNIRGui/src/main/icons/mac/512.png
MJOLNIRGui/src/main/python/AboutDialog.py
MJOLNIRGui/src/main/python/AboutDialog.pyo
MJOLNIRGui/src/main/python/AppContextEmulator.py
MJOLNIRGui/src/main/python/AppContextEmulator.pyo
MJOLNIRGui/src/main/python/DataModels.py
MJOLNIRGui/src/main/python/DataModels.pyo
MJOLNIRGui/src/main/python/GuiStates.py
MJOLNIRGui/src/main/python/GuiStates.pyo
MJOLNIRGui/src/main/python/HelpDialog.py
MJOLNIRGui/src/main/python/HelpDialog.pyo
MJOLNIRGui/src/main/python/LICENSE
MJOLNIRGui/src/main/python/MJOLNIR_Data.py
MJOLNIRGui/src/main/python/MJOLNIR_Data.pyo
MJOLNIRGui/src/main/python/MJOLNIR_GUI.py
MJOLNIRGui/src/main/python/MJOLNIR_GUI.pyo
MJOLNIRGui/src/main/python/README.md
MJOLNIRGui/src/main/python/StateMachine.py
MJOLNIRGui/src/main/python/StateMachine.pyo
MJOLNIRGui/src/main/python/_tools.py
MJOLNIRGui/src/main/python/_tools.pyo
MJOLNIRGui/src/main/python/generateScripts.py
MJOLNIRGui/src/main/python/generateScripts.pyo
MJOLNIRGui/src/main/python/main.py
MJOLNIRGui-1.0.7.dist-info/LICENSE
MJOLNIRGui-1.0.7.dist-info/METADATA
MJOLNIRGui-1.0.7.dist-info/WHEEL
MJOLNIRGui-1.0.7.dist-info/entry_points.txt
MJOLNIRGui-1.0.7.dist-info/top_level.txt
MJOLNIRGui-1.0.7.dist-info/RECORD
