Metadata-Version: 2.1
Name: MJOLNIRGui
Version: 1.0.7
Summary: Neutron Scattering software suite.
Home-page: https://github.com/MJOLNIRPackage/MJOLNIR-GUI
Author: MJOLNIRPackage
Author-email: MJOLNIRPackage@gmail.dk
License: MPL-2.0
Platform: UNKNOWN
Classifier: Development Status :: 3 - Alpha
Classifier: Programming Language :: Python :: 3.6
Classifier: Programming Language :: Python :: 3.7
Classifier: Programming Language :: Python :: 3.8
Classifier: Programming Language :: Python :: 3.9
Requires-Python: >=3.5
License-File: LICENSE
Requires-Dist: pip (>=20)
Requires-Dist: PyQt5
Requires-Dist: MJOLNIR (>=1.3.0)
Requires-Dist: ufit (>=1.4.0)
